<?xml version="1.0" encoding="UTF-8"?>
<con:resource name="/user/logout" path="/user/logout" id="50eddac5-251d-4543-b9ce-4002eccc4918" xmlns:xsi="http://www.w3.org/2001/XMLSchema-instance" xmlns:con="http://eviware.com/soapui/config"><con:settings><con:setting id="50eddac5-251d-4543-b9ce-4002eccc4918fileName">%2Fuser%2Flogout</con:setting></con:settings><con:parameters/><con:method name="logoutUser" id="172f498c-f7f5-4ce8-873e-19999e3608ec" method="GET"><con:description>
Logs out current logged in user session</con:description><con:settings/><con:parameters/><con:representation type="RESPONSE"><con:mediaType>application/xml</con:mediaType><con:status/><con:params/></con:representation><con:representation type="RESPONSE"><con:mediaType>application/json</con:mediaType><con:status/><con:params/></con:representation><con:request name="Request 1" id="3859272b-0406-4123-abd1-e56b2e4cc47d" mediaType="application/json"><con:settings/><con:endpoint>http://petstore.swagger.io</con:endpoint><con:credentials><con:selectedAuthProfile>No Authorization</con:selectedAuthProfile><con:authType>No Authorization</con:authType></con:credentials><con:parameters/></con:request></con:method></con:resource>